<List><Value><Table><Entry><Key>Name</Key><Value>Royal Guard</Value></Entry><Entry><Key>AssetId</Key><Value>21011090</Value></Entry><Entry><Key>AssetSetId</Key><Value>841</Value></Entry><Entry><Key>AssetVersionId</Key><Value>52788626</Value></Entry><Entry><Key>CreatorName</Key><Value>Hicup789</Value></Entry><Entry><Key>IsTrusted</Key><Value>True</Value></Entry></Table></Value><Value><Table><Entry><Key>Name</Key><Value>Kitten Mask</Value></Entry><Entry><Key>AssetId</Key><Value>20916666</Value></Entry><Entry><Key>AssetSetId</Key><Value>841</Value></Entry><Entry><Key>AssetVersionId</Key><Value>52547933</Value></Entry><Entry><Key>CreatorName</Key><Value>Hicup789</Value></Entry><Entry><Key>IsTrusted</Key><Value>True</Value></Entry></Table></Value><Value><Table><Entry><Key>Name</Key><Value>Hercules Hair</Value></Entry><Entry><Key>AssetId</Key><Value>20373830</Value></Entry><Entry><Key>AssetSetId</Key><Value>841</Value></Entry><Entry><Key>AssetVersionId</Key><Value>51243581</Value></Entry><Entry><Key>CreatorName</Key><Value>Hicup789</Value></Entry><Entry><Key>IsTrusted</Key><Value>True</Value></Entry></Table></Value><Value><Table><Entry><Key>Name</Key><Value>Golden Warrior</Value></Entry><Entry><Key>AssetId</Key><Value>20082127</Value></Entry><Entry><Key>AssetSetId</Key><Value>841</Value></Entry><Entry><Key>AssetVersionId</Key><Value>50538474</Value></Entry><Entry><Key>CreatorName</Key><Value>Hicup789</Value></Entry><Entry><Key>IsTrusted</Key><Value>True</Value></Entry></Table></Value><Value><Table><Entry><Key>Name</Key><Value>You just got... RICK ROLL'D!</Value></Entry><Entry><Key>AssetId</Key><Value>18759296</Value></Entry><Entry><Key>AssetSetId</Key><Value>841</Value></Entry><Entry><Key>AssetVersionId</Key><Value>47244075</Value></Entry><Entry><Key>CreatorName</Key><Value>Hicup789</Value></Entry><Entry><Key>IsTrusted</Key><Value>True</Value></Entry></Table></Value><Value><Table><Entry><Key>Name</Key><Value>Halloween Fedora</Value></Entry><Entry><Key>AssetId</Key><Value>17413664</Value></Entry><Entry><Key>AssetSetId</Key><Value>841</Value></Entry><Entry><Key>AssetVersionId</Key><Value>44202585</Value></Entry><Entry><Key>CreatorName</Key><Value>Hicup789</Value></Entry><Entry><Key>IsTrusted</Key><Value>True</Value></Entry></Table></Value><Value><Table><Entry><Key>Name</Key><Value>Blue Storm Motocross Helmet</Value></Entry><Entry><Key>AssetId</Key><Value>21051157</Value></Entry><Entry><Key>AssetSetId</Key><Value>841</Value></Entry><Entry><Key>AssetVersionId</Key><Value>52854972</Value></Entry><Entry><Key>CreatorName</Key><Value>Hicup789</Value></Entry><Entry><Key>IsTrusted</Key><Value>True</Value></Entry></Table></Value><Value><Table><Entry><Key>Name</Key><Value>Red Flames Stunt Helm</Value></Entry><Entry><Key>AssetId</Key><Value>21083128</Value></Entry><Entry><Key>AssetSetId</Key><Value>841</Value></Entry><Entry><Key>AssetVersionId</Key><Value>52917837</Value></Entry><Entry><Key>CreatorName</Key><Value>Hicup789</Value></Entry><Entry><Key>IsTrusted</Key><Value>True</Value></Entry></Table></Value><Value><Table><Entry><Key>Name</Key><Value>Racing Flag</Value></Entry><Entry><Key>AssetId</Key><Value>21203377</Value></Entry><Entry><Key>AssetSetId</Key><Value>841</Value></Entry><Entry><Key>AssetVersionId</Key><Value>53250614</Value></Entry><Entry><Key>CreatorName</Key><Value>Hicup789</Value></Entry><Entry><Key>IsTrusted</Key><Value>True</Value></Entry></Table></Value><Value><Table><Entry><Key>Name</Key><Value>Checkerd Crown of Chess</Value></Entry><Entry><Key>AssetId</Key><Value>21254745</Value></Entry><Entry><Key>AssetSetId</Key><Value>841</Value></Entry><Entry><Key>AssetVersionId</Key><Value>53292209</Value></Entry><Entry><Key>CreatorName</Key><Value>Hicup789</Value></Entry><Entry><Key>IsTrusted</Key><Value>True</Value></Entry></Table></Value><Value><Table><Entry><Key>Name</Key><Value>Flamed Paintball Mask</Value></Entry><Entry><Key>AssetId</Key><Value>21370829</Value></Entry><Entry><Key>AssetSetId</Key><Value>841</Value></Entry><Entry><Key>AssetVersionId</Key><Value>53542783</Value></Entry><Entry><Key>CreatorName</Key><Value>Hicup789</Value></Entry><Entry><Key>IsTrusted</Key><Value>True</Value></Entry></Table></Value><Value><Table><Entry><Key>Name</Key><Value>The Love Guru</Value></Entry><Entry><Key>AssetId</Key><Value>22086305</Value></Entry><Entry><Key>AssetSetId</Key><Value>841</Value></Entry><Entry><Key>AssetVersionId</Key><Value>55306128</Value></Entry><Entry><Key>CreatorName</Key><Value>Hicup789</Value></Entry><Entry><Key>IsTrusted</Key><Value>True</Value></Entry></Table></Value><Value><Table><Entry><Key>Name</Key><Value>Spring &quot;Spring&quot; :(</Value></Entry><Entry><Key>AssetId</Key><Value>24796684</Value></Entry><Entry><Key>AssetSetId</Key><Value>841</Value></Entry><Entry><Key>AssetVersionId</Key><Value>61793934</Value></Entry><Entry><Key>CreatorName</Key><Value>Hicup789</Value></Entry><Entry><Key>IsTrusted</Key><Value>True</Value></Entry></Table></Value><Value><Table><Entry><Key>Name</Key><Value>Famous Quapod Painting</Value></Entry><Entry><Key>AssetId</Key><Value>25587312</Value></Entry><Entry><Key>AssetSetId</Key><Value>841</Value></Entry><Entry><Key>AssetVersionId</Key><Value>63717625</Value></Entry><Entry><Key>CreatorName</Key><Value>Hicup789</Value></Entry><Entry><Key>IsTrusted</Key><Value>True</Value></Entry></Table></Value><Value><Table><Entry><Key>Name</Key><Value>Skybox Painting</Value></Entry><Entry><Key>AssetId</Key><Value>25587324</Value></Entry><Entry><Key>AssetSetId</Key><Value>841</Value></Entry><Entry><Key>AssetVersionId</Key><Value>63717661</Value></Entry><Entry><Key>CreatorName</Key><Value>Hicup789</Value></Entry><Entry><Key>IsTrusted</Key><Value>True</Value></Entry></Table></Value><Value><Table><Entry><Key>Name</Key><Value>Roblox Fan Cap</Value></Entry><Entry><Key>AssetId</Key><Value>26561393</Value></Entry><Entry><Key>AssetSetId</Key><Value>841</Value></Entry><Entry><Key>AssetVersionId</Key><Value>66023130</Value></Entry><Entry><Key>CreatorName</Key><Value>Hicup789</Value></Entry><Entry><Key>IsTrusted</Key><Value>True</Value></Entry></Table></Value><Value><Table><Entry><Key>Name</Key><Value>Skybox Shades</Value></Entry><Entry><Key>AssetId</Key><Value>25217562</Value></Entry><Entry><Key>AssetSetId</Key><Value>841</Value></Entry><Entry><Key>AssetVersionId</Key><Value>62847220</Value></Entry><Entry><Key>CreatorName</Key><Value>Hicup789</Value></Entry><Entry><Key>IsTrusted</Key><Value>True</Value></Entry></Table></Value><Value><Table><Entry><Key>Name</Key><Value>Dark Lords Helmet</Value></Entry><Entry><Key>AssetId</Key><Value>25651564</Value></Entry><Entry><Key>AssetSetId</Key><Value>841</Value></Entry><Entry><Key>AssetVersionId</Key><Value>63872209</Value></Entry><Entry><Key>CreatorName</Key><Value>Hicup789</Value></Entry><Entry><Key>IsTrusted</Key><Value>True</Value></Entry></Table></Value><Value><Table><Entry><Key>Name</Key><Value>Waffle Cone Cap [Read Description]</Value></Entry><Entry><Key>AssetId</Key><Value>30835824</Value></Entry><Entry><Key>AssetSetId</Key><Value>841</Value></Entry><Entry><Key>AssetVersionId</Key><Value>76225353</Value></Entry><Entry><Key>CreatorName</Key><Value>Hicup789</Value></Entry><Entry><Key>IsTrusted</Key><Value>True</Value></Entry></Table></Value><Value><Table><Entry><Key>Name</Key><Value>Cowboy and Alien Tophat</Value></Entry><Entry><Key>AssetId</Key><Value>59106745</Value></Entry><Entry><Key>AssetSetId</Key><Value>841</Value></Entry><Entry><Key>AssetVersionId</Key><Value>143713668</Value></Entry><Entry><Key>CreatorName</Key><Value>Hicup789</Value></Entry><Entry><Key>IsTrusted</Key><Value>True</Value></Entry></Table></Value><Value><Table><Entry><Key>Name</Key><Value>Buildermans Classy yet Stylish Shades</Value></Entry><Entry><Key>AssetId</Key><Value>50766148</Value></Entry><Entry><Key>AssetSetId</Key><Value>841</Value></Entry><Entry><Key>AssetVersionId</Key><Value>120664766</Value></Entry><Entry><Key>CreatorName</Key><Value>Hicup789</Value></Entry><Entry><Key>IsTrusted</Key><Value>True</Value></Entry></Table></Value><Value><Table><Entry><Key>Name</Key><Value>Party Glasses</Value></Entry><Entry><Key>AssetId</Key><Value>24358209</Value></Entry><Entry><Key>AssetSetId</Key><Value>841</Value></Entry><Entry><Key>AssetVersionId</Key><Value>60734242</Value></Entry><Entry><Key>CreatorName</Key><Value>Hicup789</Value></Entry><Entry><Key>IsTrusted</Key><Value>True</Value></Entry></Table></Value><Value><Table><Entry><Key>Name</Key><Value>The Great Shootout</Value></Entry><Entry><Key>AssetId</Key><Value>22861392</Value></Entry><Entry><Key>AssetSetId</Key><Value>841</Value></Entry><Entry><Key>AssetVersionId</Key><Value>57001150</Value></Entry><Entry><Key>CreatorName</Key><Value>Hicup789</Value></Entry><Entry><Key>IsTrusted</Key><Value>True</Value></Entry></Table></Value></List>